<pkg-contents spec="1.12"><f n="2dx" o="marheit" g="staff" p="16877" pt="/Users/marheit/2dx" m="true" t="file"><f n="2dx_image" o="marheit" g="staff" p="16893"><f n="2dx_image.app" o="marheit" g="staff" p="16893"><f n="Contents" o="marheit" g="staff" p="16893"><f n="Frameworks" o="marheit" g="staff" p="16893"><f n="phonon.framework" o="marheit" g="staff" p="16893"><f n="Versions" o="marheit" g="staff" p="16893"><f n="4" o="marheit" g="staff" p="16893"><f n="phonon" o="marheit" g="staff" p="33204"><mod>mode</mod></f><mod>mode</mod></f><mod>mode</mod></f><mod>mode</mod></f><f n="QtCore.framework" o="marheit" g="staff" p="16893"><f n="Versions" o="marheit" g="staff" p="16893"><f n="4" o="marheit" g="staff" p="16893"><f n="QtCore" o="marheit" g="staff" p="33204"><mod>mode</mod></f><mod>mode</mod></f><mod>mode</mod></f><mod>mode</mod></f><f n="QtDBus.framework" o="marheit" g="staff" p="16893"><f n="Versions" o="marheit" g="staff" p="16893"><f n="4" o="marheit" g="staff" p="16893"><f n="QtDBus" o="marheit" g="staff" p="33204"><mod>mode</mod></f><mod>mode</mod></f><mod>mode</mod></f><mod>mode</mod></f><f n="QtGui.framework" o="marheit" g="staff" p="16893"><f n="Versions" o="marheit" g="staff" p="16893"><f n="4" o="marheit" g="staff" p="16893"><f n="QtGui" o="marheit" g="staff" p="33204"><mod>mode</mod></f><mod>mode</mod></f><mod>mode</mod></f><mod>mode</mod></f><f n="QtNetwork.framework" o="marheit" g="staff" p="16893"><f n="Versions" o="marheit" g="staff" p="16893"><f n="4" o="marheit" g="staff" p="16893"><f n="QtNetwork" o="marheit" g="staff" p="33204"><mod>mode</mod></f><mod>mode</mod></f><mod>mode</mod></f><mod>mode</mod></f><f n="QtOpenGL.framework" o="marheit" g="staff" p="16893"><f n="Versions" o="marheit" g="staff" p="16893"><f n="4" o="marheit" g="staff" p="16893"><f n="QtOpenGL" o="marheit" g="staff" p="33204"><mod>mode</mod></f><mod>mode</mod></f><mod>mode</mod></f><mod>mode</mod></f><f n="QtScript.framework" o="marheit" g="staff" p="16893"><f n="Versions" o="marheit" g="staff" p="16893"><f n="4" o="marheit" g="staff" p="16893"><f n="QtScript" o="marheit" g="staff" p="33204"><mod>mode</mod></f><mod>mode</mod></f><mod>mode</mod></f><mod>mode</mod></f><f n="QtWebKit.framework" o="marheit" g="staff" p="16893"><f n="Versions" o="marheit" g="staff" p="16893"><f n="4" o="marheit" g="staff" p="16893"><f n="QtWebKit" o="marheit" g="staff" p="33204"><mod>mode</mod></f><mod>mode</mod></f><mod>mode</mod></f><mod>mode</mod></f><f n="QtXml.framework" o="marheit" g="staff" p="16893"><f n="Versions" o="marheit" g="staff" p="16893"><f n="4" o="marheit" g="staff" p="16893"><f n="QtXml" o="marheit" g="staff" p="33204"><mod>mode</mod></f><mod>mode</mod></f><mod>mode</mod></f><mod>mode</mod></f><f n="QtXmlPatterns.framework" o="marheit" g="staff" p="16893"><f n="Versions" o="marheit" g="staff" p="16893"><f n="4" o="marheit" g="staff" p="16893"><f n="QtXmlPatterns" o="marheit" g="staff" p="33204"><mod>mode</mod></f><mod>mode</mod></f><mod>mode</mod></f><mod>mode</mod></f><mod>mode</mod></f><f n="Info.plist" o="marheit" g="staff" p="33204"><mod>mode</mod></f><f n="MacOS" o="marheit" g="staff" p="16893"><f n="2dx_image" o="marheit" g="staff" p="33277"><mod>mode</mod></f><f n="libfftw3f.3.dylib" o="marheit" g="staff" p="33277"><mod>mode</mod></f><f n="libfftw3f_threads.3.dylib" o="marheit" g="staff" p="33277"><mod>mode</mod></f><mod>mode</mod></f><f n="PlugIns" o="marheit" g="staff" p="16893"><f n="imageformats" o="marheit" g="staff" p="16893"><f n="libqgif.dylib" o="marheit" g="staff" p="33277"><mod>mode</mod></f><f n="libqico.dylib" o="marheit" g="staff" p="33277"><mod>mode</mod></f><f n="libqjpeg.dylib" o="marheit" g="staff" p="33277"><mod>mode</mod></f><f n="libqmng.dylib" o="marheit" g="staff" p="33277"><mod>mode</mod></f><f n="libqsvg.dylib" o="marheit" g="staff" p="33277"><mod>mode</mod></f><f n="libqtiff.dylib" o="marheit" g="staff" p="33277"><mod>mode</mod></f><mod>mode</mod></f><mod>mode</mod></f><f n="Resources" o="marheit" g="staff" p="16893"><f n="icon_OSX.icns" o="marheit" g="staff" p="33277"><mod>mode</mod></f><f n="qt.conf" o="marheit" g="staff" p="33204"><mod>mode</mod></f><f n="qt_menu.nib" o="marheit" g="staff" p="16893"><f n="classes.nib" o="marheit" g="staff" p="33204"><mod>mode</mod></f><f n="info.nib" o="marheit" g="staff" p="33204"><mod>mode</mod></f><f n="keyedobjects.nib" o="marheit" g="staff" p="33204"><mod>mode</mod></f><mod>mode</mod></f><mod>mode</mod></f><mod>mode</mod></f><mod>mode</mod></f><f n="bin" o="marheit" g="staff" p="16893"><f n="2dx_allspacea.exe" o="marheit" g="staff" p="33277"><mod>mode</mod></f><f n="2dx_avrgamphs.exe" o="marheit" g="staff" p="33277"><mod>mode</mod></f><f n="2dx_boximage.exe" o="marheit" g="staff" p="33277"><mod>mode</mod></f><f n="2dx_byteSwap.exe" o="marheit" g="staff" p="33277"><mod>mode</mod></f><f n="2dx_calangle.exe" o="marheit" g="staff" p="33277"><mod>mode</mod></f><f n="2dx_calcmag.exe" o="marheit" g="staff" p="33277"><mod>mode</mod></f><f n="2dx_callat.exe" o="marheit" g="staff" p="33277"><mod>mode</mod></f><f n="2dx_ccunbendh.exe" o="marheit" g="staff" p="33277"><mod>mode</mod></f><f n="2dx_ccunbendk.exe" o="marheit" g="staff" p="33277"><mod>mode</mod></f><f n="2dx_centric.exe" o="marheit" g="staff" p="33277"><mod>mode</mod></f><f n="2dx_centric2.exe" o="marheit" g="staff" p="33277"><mod>mode</mod></f><f n="2dx_checklat3.exe" o="marheit" g="staff" p="33277"><mod>mode</mod></f><f n="2dx_CompleteFriedel.exe" o="marheit" g="staff" p="33277"><mod>mode</mod></f><f n="2dx_ctfapplyk.exe" o="marheit" g="staff" p="33277"><mod>mode</mod></f><f n="2dx_ctffind3.exe" o="marheit" g="staff" p="33277"><mod>mode</mod></f><f n="2dx_ctftilt.exe" o="marheit" g="staff" p="33277"><mod>mode</mod></f><f n="2dx_DATAtranslate.exe" o="marheit" g="staff" p="33277"><mod>mode</mod></f><f n="2dx_emtilt.exe" o="marheit" g="staff" p="33277"><mod>mode</mod></f><f n="2dx_endianTest.exe" o="marheit" g="staff" p="33277"><mod>mode</mod></f><f n="2dx_fftrans.exe" o="marheit" g="staff" p="33277"><mod>mode</mod></f><f n="2dx_findlat.exe" o="marheit" g="staff" p="33277"><mod>mode</mod></f><f n="2dx_getlat.exe" o="marheit" g="staff" p="33277"><mod>mode</mod></f><f n="2dx_getnumber.exe" o="marheit" g="staff" p="33277"><mod>mode</mod></f><f n="2dx_getspot.exe" o="marheit" g="staff" p="33277"><mod>mode</mod></f><f n="2dx_hand.exe" o="marheit" g="staff" p="33277"><mod>mode</mod></f><f n="2dx_hklclean.exe" o="marheit" g="staff" p="33277"><mod>mode</mod></f><f n="2dx_hklsym.exe" o="marheit" g="staff" p="33277"><mod>mode</mod></f><f n="2dx_latconvert.exe" o="marheit" g="staff" p="33277"><mod>mode</mod></f><f n="2dx_laterror.exe" o="marheit" g="staff" p="33277"><mod>mode</mod></f><f n="2dx_latlinek.exe" o="marheit" g="staff" p="33277"><mod>mode</mod></f><f n="2dx_latlinprescal.exe" o="marheit" g="staff" p="33277"><mod>mode</mod></f><f n="2dx_lencalc.exe" o="marheit" g="staff" p="33277"><mod>mode</mod></f><f n="2dx_maketrana.exe" o="marheit" g="staff" p="33277"><mod>mode</mod></f><f n="2dx_merge_compileA.exe" o="marheit" g="staff" p="33277"><mod>mode</mod></f><f n="2dx_merge_compileB.exe" o="marheit" g="staff" p="33277"><mod>mode</mod></f><f n="2dx_merge_compileM.exe" o="marheit" g="staff" p="33277"><mod>mode</mod></f><f n="2dx_merge_compilePLT.exe" o="marheit" g="staff" p="33277"><mod>mode</mod></f><f n="2dx_merge_eval.exe" o="marheit" g="staff" p="33277"><mod>mode</mod></f><f n="2dx_merge_inventory.exe" o="marheit" g="staff" p="33277"><mod>mode</mod></f><f n="2dx_merge_modifyImageParameter.exe" o="marheit" g="staff" p="33277"><mod>mode</mod></f><f n="2dx_mergeeval.exe" o="marheit" g="staff" p="33277"><mod>mode</mod></f><f n="2dx_ML.exe" o="marheit" g="staff" p="33277"><mod>mode</mod></f><f n="2dx_mmboxa.exe" o="marheit" g="staff" p="33277"><mod>mode</mod></f><f n="2dx_mmlatref.exe" o="marheit" g="staff" p="33277"><mod>mode</mod></f><f n="2dx_modifypolygon.exe" o="marheit" g="staff" p="33277"><mod>mode</mod></f><f n="2dx_origtiltk.exe" o="marheit" g="staff" p="33277"><mod>mode</mod></f><f n="2dx_peaksearch.exe" o="marheit" g="staff" p="33277"><mod>mode</mod></f><f n="2dx_periodogram.exe" o="marheit" g="staff" p="33277"><mod>mode</mod></f><f n="2dx_permutate.exe" o="marheit" g="staff" p="33277"><mod>mode</mod></f><f n="2dx_pickautok.exe" o="marheit" g="staff" p="33277"><mod>mode</mod></f><f n="2dx_plotres.exe" o="marheit" g="staff" p="33277"><mod>mode</mod></f><f n="2dx_plotreska.exe" o="marheit" g="staff" p="33277"><mod>mode</mod></f><f n="2dx_pltiltk.exe" o="marheit" g="staff" p="33277"><mod>mode</mod></f><f n="2dx_powerhisto.exe" o="marheit" g="staff" p="33277"><mod>mode</mod></f><f n="2dx_prep.exe" o="marheit" g="staff" p="33277"><mod>mode</mod></f><f n="2dx_primes.exe" o="marheit" g="staff" p="33277"><mod>mode</mod></f><f n="2dx_quadserchk-2.exe" o="marheit" g="staff" p="33277"><mod>mode</mod></f><f n="2dx_reciproc.exe" o="marheit" g="staff" p="33277"><mod>mode</mod></f><f n="2dx_spotfilter.exe" o="marheit" g="staff" p="33277"><mod>mode</mod></f><f n="2dx_spotgenerator.exe" o="marheit" g="staff" p="33277"><mod>mode</mod></f><f n="2dx_spotrefine.exe" o="marheit" g="staff" p="33277"><mod>mode</mod></f><f n="2dx_taperedgek.exe" o="marheit" g="staff" p="33277"><mod>mode</mod></f><f n="2dx_tiltgeom.exe" o="marheit" g="staff" p="33277"><mod>mode</mod></f><f n="2dx_tiltgeom2.exe" o="marheit" g="staff" p="33277"><mod>mode</mod></f><f n="2dx_ttboxk.exe" o="marheit" g="staff" p="33277"><mod>mode</mod></f><f n="2dx_ttboxref.exe" o="marheit" g="staff" p="33277"><mod>mode</mod></f><f n="2dx_ttmask.exe" o="marheit" g="staff" p="33277"><mod>mode</mod></f><f n="2dx_ttrefine.exe" o="marheit" g="staff" p="33277"><mod>mode</mod></f><f n="2dx_twofile.exe" o="marheit" g="staff" p="33277"><mod>mode</mod></f><f n="angback.exe" o="marheit" g="staff" p="33277"><mod>mode</mod></f><f n="autocorrl.exe" o="marheit" g="staff" p="33277"><mod>mode</mod></f><f n="autoindexk.exe" o="marheit" g="staff" p="33277"><mod>mode</mod></f><f n="avrgamphs.exe" o="marheit" g="staff" p="33277"><mod>mode</mod></f><f n="backautok.exe" o="marheit" g="staff" p="33277"><mod>mode</mod></f><f n="boxim.exe" o="marheit" g="staff" p="33277"><mod>mode</mod></f><f n="byte_swap_map.exe" o="marheit" g="staff" p="33277"><mod>mode</mod></f><f n="centricp2.exe" o="marheit" g="staff" p="33277"><mod>mode</mod></f><f n="centricp4.exe" o="marheit" g="staff" p="33277"><mod>mode</mod></f><f n="ctfcalck.exe" o="marheit" g="staff" p="33277"><mod>mode</mod></f><f n="ctffinda.exe" o="marheit" g="staff" p="33277"><mod>mode</mod></f><f n="ctfsearch2.exe" o="marheit" g="staff" p="33277"><mod>mode</mod></f><f n="ctftilt.exe" o="marheit" g="staff" p="33277"><mod>mode</mod></f><f n="curvy2k.exe" o="marheit" g="staff" p="33277"><mod>mode</mod></f><f n="deftilt.exe" o="marheit" g="staff" p="33277"><mod>mode</mod></f><f n="divideq.exe" o="marheit" g="staff" p="33277"><mod>mode</mod></f><f n="floatcompare.exe" o="marheit" g="staff" p="33277"><mod>mode</mod></f><f n="getmax.exe" o="marheit" g="staff" p="33277"><mod>mode</mod></f><f n="hcut.exe" o="marheit" g="staff" p="33277"><mod>mode</mod></f><f n="header.exe" o="marheit" g="staff" p="33277"><mod>mode</mod></f><f n="histok.exe" o="marheit" g="staff" p="33277"><mod>mode</mod></f><f n="image_convert.exe" o="marheit" g="staff" p="33277"><mod>mode</mod></f><f n="labelh.exe" o="marheit" g="staff" p="33277"><mod>mode</mod></f><f n="laserplot.exe" o="marheit" g="staff" p="33277"><mod>mode</mod></f><f n="latlinprescal.exe" o="marheit" g="staff" p="33277"><mod>mode</mod></f><f n="masktrana.exe" o="marheit" g="staff" p="33277"><mod>mode</mod></f><f n="mmtomklcf.exe" o="marheit" g="staff" p="33277"><mod>mode</mod></f><f n="mrc2tif.exe" o="marheit" g="staff" p="33277"><mod>mode</mod></f><f n="oddremove.exe" o="marheit" g="staff" p="33277"><mod>mode</mod></f><f n="padbox.exe" o="marheit" g="staff" p="33277"><mod>mode</mod></f><f n="prepmklcf.exe" o="marheit" g="staff" p="33277"><mod>mode</mod></f><f n="refineorigin.exe" o="marheit" g="staff" p="33277"><mod>mode</mod></f><f n="scalimamp3d.exe" o="marheit" g="staff" p="33277"><mod>mode</mod></f><f n="tif2mrc.exe" o="marheit" g="staff" p="33277"><mod>mode</mod></f><f n="trmask.exe" o="marheit" g="staff" p="33277"><mod>mode</mod></f><f n="twofile.exe" o="marheit" g="staff" p="33277"><mod>mode</mod></f><f n="twolattk.exe" o="marheit" g="staff" p="33277"><mod>mode</mod></f><mod>mode</mod></f><f n="scripts-custom" o="marheit" g="staff" p="16893"><f n="2dx_all_parameters.script" o="marheit" g="staff" p="33277"><mod>mode</mod></f><f n="2dx_allspace.script" o="marheit" g="staff" p="33277"><mod>mode</mod></f><f n="2dx_cleanup.script" o="marheit" g="staff" p="33277"><mod>mode</mod></f><f n="2dx_evaluateLattice.script" o="marheit" g="staff" p="33277"><mod>mode</mod></f><f n="2dx_fourierSpots.script" o="marheit" g="staff" p="33277"><mod>mode</mod></f><f n="2dx_generateSymMap.script" o="marheit" g="staff" p="33277"><mod>mode</mod></f><f n="2dx_inventory.script" o="marheit" g="staff" p="33277"><mod>mode</mod></f><f n="2dx_maskCrystal.script" o="marheit" g="staff" p="33277"><mod>mode</mod></f><f n="2dx_ModifAmplitude.script" o="marheit" g="staff" p="33277"><mod>mode</mod></f><f n="2dx_phaseorigin.script" o="marheit" g="staff" p="33277"><mod>mode</mod></f><f n="2dx_refine_unbend1.script" o="marheit" g="staff" p="33277"><mod>mode</mod></f><f n="2dx_refine_unbend2.script" o="marheit" g="staff" p="33277"><mod>mode</mod></f><f n="2dx_refinedefocus.script" o="marheit" g="staff" p="33277"><mod>mode</mod></f><f n="2dx_refinespots.script" o="marheit" g="staff" p="33277"><mod>mode</mod></f><f n="2dx_refinetilt.script" o="marheit" g="staff" p="33277"><mod>mode</mod></f><mod>mode</mod></f><f n="scripts-standard" o="marheit" g="staff" p="16893"><f n="2dx_applyCTF.script" o="marheit" g="staff" p="33277"><mod>mode</mod></f><f n="2dx_fftrans.script" o="marheit" g="staff" p="33277"><mod>mode</mod></f><f n="2dx_generateMAP.script" o="marheit" g="staff" p="33277"><mod>mode</mod></f><f n="2dx_getDefocusTilt.script" o="marheit" g="staff" p="33277"><mod>mode</mod></f><f n="2dx_getLattice.script" o="marheit" g="staff" p="33277"><mod>mode</mod></f><f n="2dx_getSampleTilt.script" o="marheit" g="staff" p="33277"><mod>mode</mod></f><f n="2dx_getspots.script" o="marheit" g="staff" p="33277"><mod>mode</mod></f><f n="2dx_getspots1.script" o="marheit" g="staff" p="33277"><mod>mode</mod></f><f n="2dx_initialize.script" o="marheit" g="staff" p="33277"><mod>mode</mod></f><f n="2dx_max_likelihood.script" o="marheit" g="staff" p="33277"><mod>mode</mod></f><f n="2dx_refineLattice.script" o="marheit" g="staff" p="33277"><mod>mode</mod></f><f n="2dx_refineParams.script" o="marheit" g="staff" p="33277"><mod>mode</mod></f><f n="2dx_unbend1.script" o="marheit" g="staff" p="33277"><mod>mode</mod></f><f n="2dx_unbend2.script" o="marheit" g="staff" p="33277"><mod>mode</mod></f><f n="2dx_unbendSyn.script" o="marheit" g="staff" p="33277"><mod>mode</mod></f><mod>mode</mod></f><mod>mode</mod></f><f n="2dx_logbrowser" o="marheit" g="staff" p="16893"><f n="2dx_logbrowser.app" o="marheit" g="staff" p="16893"><f n="Contents" o="marheit" g="staff" p="16893"><f n="Frameworks" o="marheit" g="staff" p="16893"><f n="QtCore.framework" o="marheit" g="staff" p="16893"><f n="Versions" o="marheit" g="staff" p="16893"><f n="4" o="marheit" g="staff" p="16893"><f n="QtCore" o="marheit" g="staff" p="33204"><mod>mode</mod></f><mod>mode</mod></f><mod>mode</mod></f><mod>mode</mod></f><f n="QtGui.framework" o="marheit" g="staff" p="16893"><f n="Versions" o="marheit" g="staff" p="16893"><f n="4" o="marheit" g="staff" p="16893"><f n="QtGui" o="marheit" g="staff" p="33204"><mod>mode</mod></f><mod>mode</mod></f><mod>mode</mod></f><mod>mode</mod></f><mod>mode</mod></f><f n="Info.plist" o="marheit" g="staff" p="33204"><mod>mode</mod></f><f n="MacOS" o="marheit" g="staff" p="16893"><f n="2dx_logbrowser" o="marheit" g="staff" p="33277"><mod>mode</mod></f><mod>mode</mod></f><f n="Resources" o="marheit" g="staff" p="16893"><f n="icon_OSX.icns" o="marheit" g="staff" p="33277"><mod>mode</mod></f><f n="qt.conf" o="marheit" g="staff" p="33204"><mod>mode</mod></f><f n="qt_menu.nib" o="marheit" g="staff" p="16893"><f n="classes.nib" o="marheit" g="staff" p="33204"><mod>mode</mod></f><f n="info.nib" o="marheit" g="staff" p="33204"><mod>mode</mod></f><f n="keyedobjects.nib" o="marheit" g="staff" p="33204"><mod>mode</mod></f><mod>mode</mod></f><mod>mode</mod></f><mod>mode</mod></f><mod>mode</mod></f><mod>mode</mod></f><f n="2dx_merge" o="marheit" g="staff" p="16893"><f n="2dx_merge.app" o="marheit" g="staff" p="16893"><f n="Contents" o="marheit" g="staff" p="16893"><f n="Frameworks" o="marheit" g="staff" p="16893"><f n="phonon.framework" o="marheit" g="staff" p="16893"><f n="Versions" o="marheit" g="staff" p="16893"><f n="4" o="marheit" g="staff" p="16893"><f n="phonon" o="marheit" g="staff" p="33204"><mod>mode</mod></f><mod>mode</mod></f><mod>mode</mod></f><mod>mode</mod></f><f n="QtCore.framework" o="marheit" g="staff" p="16893"><f n="Versions" o="marheit" g="staff" p="16893"><f n="4" o="marheit" g="staff" p="16893"><f n="QtCore" o="marheit" g="staff" p="33204"><mod>mode</mod></f><mod>mode</mod></f><mod>mode</mod></f><mod>mode</mod></f><f n="QtDBus.framework" o="marheit" g="staff" p="16893"><f n="Versions" o="marheit" g="staff" p="16893"><f n="4" o="marheit" g="staff" p="16893"><f n="QtDBus" o="marheit" g="staff" p="33204"><mod>mode</mod></f><mod>mode</mod></f><mod>mode</mod></f><mod>mode</mod></f><f n="QtGui.framework" o="marheit" g="staff" p="16893"><f n="Versions" o="marheit" g="staff" p="16893"><f n="4" o="marheit" g="staff" p="16893"><f n="QtGui" o="marheit" g="staff" p="33204"><mod>mode</mod></f><mod>mode</mod></f><mod>mode</mod></f><mod>mode</mod></f><f n="QtNetwork.framework" o="marheit" g="staff" p="16893"><f n="Versions" o="marheit" g="staff" p="16893"><f n="4" o="marheit" g="staff" p="16893"><f n="QtNetwork" o="marheit" g="staff" p="33204"><mod>mode</mod></f><mod>mode</mod></f><mod>mode</mod></f><mod>mode</mod></f><f n="QtOpenGL.framework" o="marheit" g="staff" p="16893"><f n="Versions" o="marheit" g="staff" p="16893"><f n="4" o="marheit" g="staff" p="16893"><f n="QtOpenGL" o="marheit" g="staff" p="33204"><mod>mode</mod></f><mod>mode</mod></f><mod>mode</mod></f><mod>mode</mod></f><f n="QtScript.framework" o="marheit" g="staff" p="16893"><f n="Versions" o="marheit" g="staff" p="16893"><f n="4" o="marheit" g="staff" p="16893"><f n="QtScript" o="marheit" g="staff" p="33204"><mod>mode</mod></f><mod>mode</mod></f><mod>mode</mod></f><mod>mode</mod></f><f n="QtWebKit.framework" o="marheit" g="staff" p="16893"><f n="Versions" o="marheit" g="staff" p="16893"><f n="4" o="marheit" g="staff" p="16893"><f n="QtWebKit" o="marheit" g="staff" p="33204"><mod>mode</mod></f><mod>mode</mod></f><mod>mode</mod></f><mod>mode</mod></f><f n="QtXml.framework" o="marheit" g="staff" p="16893"><f n="Versions" o="marheit" g="staff" p="16893"><f n="4" o="marheit" g="staff" p="16893"><f n="QtXml" o="marheit" g="staff" p="33204"><mod>mode</mod></f><mod>mode</mod></f><mod>mode</mod></f><mod>mode</mod></f><f n="QtXmlPatterns.framework" o="marheit" g="staff" p="16893"><f n="Versions" o="marheit" g="staff" p="16893"><f n="4" o="marheit" g="staff" p="16893"><f n="QtXmlPatterns" o="marheit" g="staff" p="33204"><mod>mode</mod></f><mod>mode</mod></f><mod>mode</mod></f><mod>mode</mod></f><mod>mode</mod></f><f n="Info.plist" o="marheit" g="staff" p="33204"><mod>mode</mod></f><f n="MacOS" o="marheit" g="staff" p="16893"><f n="2dx_merge" o="marheit" g="staff" p="33277"><mod>mode</mod></f><f n="libfftw3f.3.dylib" o="marheit" g="staff" p="33277"><mod>mode</mod></f><f n="libfftw3f_threads.3.dylib" o="marheit" g="staff" p="33277"><mod>mode</mod></f><mod>mode</mod></f><f n="PlugIns" o="marheit" g="staff" p="16893"><f n="imageformats" o="marheit" g="staff" p="16893"><f n="libqgif.dylib" o="marheit" g="staff" p="33277"><mod>mode</mod></f><f n="libqico.dylib" o="marheit" g="staff" p="33277"><mod>mode</mod></f><f n="libqjpeg.dylib" o="marheit" g="staff" p="33277"><mod>mode</mod></f><f n="libqmng.dylib" o="marheit" g="staff" p="33277"><mod>mode</mod></f><f n="libqsvg.dylib" o="marheit" g="staff" p="33277"><mod>mode</mod></f><f n="libqtiff.dylib" o="marheit" g="staff" p="33277"><mod>mode</mod></f><mod>mode</mod></f><mod>mode</mod></f><f n="Resources" o="marheit" g="staff" p="16893"><f n="icon.icns" o="marheit" g="staff" p="33277"><mod>mode</mod></f><f n="qt.conf" o="marheit" g="staff" p="33204"><mod>mode</mod></f><f n="qt_menu.nib" o="marheit" g="staff" p="16893"><f n="classes.nib" o="marheit" g="staff" p="33204"><mod>mode</mod></f><f n="info.nib" o="marheit" g="staff" p="33204"><mod>mode</mod></f><f n="keyedobjects.nib" o="marheit" g="staff" p="33204"><mod>mode</mod></f><mod>mode</mod></f><mod>mode</mod></f><mod>mode</mod></f><mod>mode</mod></f><f n="bin" o="marheit" g="staff" p="16893"><f n="2dx_allspacea.exe" o="marheit" g="staff" p="33277"><mod>mode</mod></f><f n="2dx_avrgamphs.exe" o="marheit" g="staff" p="33277"><mod>mode</mod></f><f n="2dx_boximage.exe" o="marheit" g="staff" p="33277"><mod>mode</mod></f><f n="2dx_byteSwap.exe" o="marheit" g="staff" p="33277"><mod>mode</mod></f><f n="2dx_calangle.exe" o="marheit" g="staff" p="33277"><mod>mode</mod></f><f n="2dx_calcmag.exe" o="marheit" g="staff" p="33277"><mod>mode</mod></f><f n="2dx_callat.exe" o="marheit" g="staff" p="33277"><mod>mode</mod></f><f n="2dx_ccunbendh.exe" o="marheit" g="staff" p="33277"><mod>mode</mod></f><f n="2dx_ccunbendk.exe" o="marheit" g="staff" p="33277"><mod>mode</mod></f><f n="2dx_centric.exe" o="marheit" g="staff" p="33277"><mod>mode</mod></f><f n="2dx_centric2.exe" o="marheit" g="staff" p="33277"><mod>mode</mod></f><f n="2dx_checklat3.exe" o="marheit" g="staff" p="33277"><mod>mode</mod></f><f n="2dx_CompleteFriedel.exe" o="marheit" g="staff" p="33277"><mod>mode</mod></f><f n="2dx_ctfapplyk.exe" o="marheit" g="staff" p="33277"><mod>mode</mod></f><f n="2dx_ctffind3.exe" o="marheit" g="staff" p="33277"><mod>mode</mod></f><f n="2dx_ctftilt.exe" o="marheit" g="staff" p="33277"><mod>mode</mod></f><f n="2dx_DATAtranslate.exe" o="marheit" g="staff" p="33277"><mod>mode</mod></f><f n="2dx_emtilt.exe" o="marheit" g="staff" p="33277"><mod>mode</mod></f><f n="2dx_endianTest.exe" o="marheit" g="staff" p="33277"><mod>mode</mod></f><f n="2dx_fftrans.exe" o="marheit" g="staff" p="33277"><mod>mode</mod></f><f n="2dx_findlat.exe" o="marheit" g="staff" p="33277"><mod>mode</mod></f><f n="2dx_getlat.exe" o="marheit" g="staff" p="33277"><mod>mode</mod></f><f n="2dx_getnumber.exe" o="marheit" g="staff" p="33277"><mod>mode</mod></f><f n="2dx_getspot.exe" o="marheit" g="staff" p="33277"><mod>mode</mod></f><f n="2dx_hand.exe" o="marheit" g="staff" p="33277"><mod>mode</mod></f><f n="2dx_hklclean.exe" o="marheit" g="staff" p="33277"><mod>mode</mod></f><f n="2dx_hklsym.exe" o="marheit" g="staff" p="33277"><mod>mode</mod></f><f n="2dx_latconvert.exe" o="marheit" g="staff" p="33277"><mod>mode</mod></f><f n="2dx_laterror.exe" o="marheit" g="staff" p="33277"><mod>mode</mod></f><f n="2dx_latlinek.exe" o="marheit" g="staff" p="33277"><mod>mode</mod></f><f n="2dx_latlinprescal.exe" o="marheit" g="staff" p="33277"><mod>mode</mod></f><f n="2dx_lencalc.exe" o="marheit" g="staff" p="33277"><mod>mode</mod></f><f n="2dx_maketrana.exe" o="marheit" g="staff" p="33277"><mod>mode</mod></f><f n="2dx_merge_compileA.exe" o="marheit" g="staff" p="33277"><mod>mode</mod></f><f n="2dx_merge_compileB.exe" o="marheit" g="staff" p="33277"><mod>mode</mod></f><f n="2dx_merge_compileM.exe" o="marheit" g="staff" p="33277"><mod>mode</mod></f><f n="2dx_merge_compilePLT.exe" o="marheit" g="staff" p="33277"><mod>mode</mod></f><f n="2dx_merge_eval.exe" o="marheit" g="staff" p="33277"><mod>mode</mod></f><f n="2dx_merge_inventory.exe" o="marheit" g="staff" p="33277"><mod>mode</mod></f><f n="2dx_merge_modifyImageParameter.exe" o="marheit" g="staff" p="33277"><mod>mode</mod></f><f n="2dx_mergeeval.exe" o="marheit" g="staff" p="33277"><mod>mode</mod></f><f n="2dx_ML.exe" o="marheit" g="staff" p="33277"><mod>mode</mod></f><f n="2dx_mmboxa.exe" o="marheit" g="staff" p="33277"><mod>mode</mod></f><f n="2dx_mmlatref.exe" o="marheit" g="staff" p="33277"><mod>mode</mod></f><f n="2dx_modifypolygon.exe" o="marheit" g="staff" p="33277"><mod>mode</mod></f><f n="2dx_origtiltk.exe" o="marheit" g="staff" p="33277"><mod>mode</mod></f><f n="2dx_peaksearch.exe" o="marheit" g="staff" p="33277"><mod>mode</mod></f><f n="2dx_periodogram.exe" o="marheit" g="staff" p="33277"><mod>mode</mod></f><f n="2dx_permutate.exe" o="marheit" g="staff" p="33277"><mod>mode</mod></f><f n="2dx_pickautok.exe" o="marheit" g="staff" p="33277"><mod>mode</mod></f><f n="2dx_plotres.exe" o="marheit" g="staff" p="33277"><mod>mode</mod></f><f n="2dx_plotreska.exe" o="marheit" g="staff" p="33277"><mod>mode</mod></f><f n="2dx_pltiltk.exe" o="marheit" g="staff" p="33277"><mod>mode</mod></f><f n="2dx_powerhisto.exe" o="marheit" g="staff" p="33277"><mod>mode</mod></f><f n="2dx_prep.exe" o="marheit" g="staff" p="33277"><mod>mode</mod></f><f n="2dx_primes.exe" o="marheit" g="staff" p="33277"><mod>mode</mod></f><f n="2dx_quadserchk-2.exe" o="marheit" g="staff" p="33277"><mod>mode</mod></f><f n="2dx_reciproc.exe" o="marheit" g="staff" p="33277"><mod>mode</mod></f><f n="2dx_spotfilter.exe" o="marheit" g="staff" p="33277"><mod>mode</mod></f><f n="2dx_spotgenerator.exe" o="marheit" g="staff" p="33277"><mod>mode</mod></f><f n="2dx_spotrefine.exe" o="marheit" g="staff" p="33277"><mod>mode</mod></f><f n="2dx_taperedgek.exe" o="marheit" g="staff" p="33277"><mod>mode</mod></f><f n="2dx_tiltgeom.exe" o="marheit" g="staff" p="33277"><mod>mode</mod></f><f n="2dx_tiltgeom2.exe" o="marheit" g="staff" p="33277"><mod>mode</mod></f><f n="2dx_ttboxk.exe" o="marheit" g="staff" p="33277"><mod>mode</mod></f><f n="2dx_ttboxref.exe" o="marheit" g="staff" p="33277"><mod>mode</mod></f><f n="2dx_ttmask.exe" o="marheit" g="staff" p="33277"><mod>mode</mod></f><f n="2dx_ttrefine.exe" o="marheit" g="staff" p="33277"><mod>mode</mod></f><f n="2dx_twofile.exe" o="marheit" g="staff" p="33277"><mod>mode</mod></f><f n="angback.exe" o="marheit" g="staff" p="33277"><mod>mode</mod></f><f n="autocorrl.exe" o="marheit" g="staff" p="33277"><mod>mode</mod></f><f n="autoindexk.exe" o="marheit" g="staff" p="33277"><mod>mode</mod></f><f n="avrgamphs.exe" o="marheit" g="staff" p="33277"><mod>mode</mod></f><f n="backautok.exe" o="marheit" g="staff" p="33277"><mod>mode</mod></f><f n="boxim.exe" o="marheit" g="staff" p="33277"><mod>mode</mod></f><f n="byte_swap_map.exe" o="marheit" g="staff" p="33277"><mod>mode</mod></f><f n="centricp2.exe" o="marheit" g="staff" p="33277"><mod>mode</mod></f><f n="centricp4.exe" o="marheit" g="staff" p="33277"><mod>mode</mod></f><f n="ctfcalck.exe" o="marheit" g="staff" p="33277"><mod>mode</mod></f><f n="ctffinda.exe" o="marheit" g="staff" p="33277"><mod>mode</mod></f><f n="ctfsearch2.exe" o="marheit" g="staff" p="33277"><mod>mode</mod></f><f n="ctftilt.exe" o="marheit" g="staff" p="33277"><mod>mode</mod></f><f n="curvy2k.exe" o="marheit" g="staff" p="33277"><mod>mode</mod></f><f n="deftilt.exe" o="marheit" g="staff" p="33277"><mod>mode</mod></f><f n="divideq.exe" o="marheit" g="staff" p="33277"><mod>mode</mod></f><f n="floatcompare.exe" o="marheit" g="staff" p="33277"><mod>mode</mod></f><f n="getmax.exe" o="marheit" g="staff" p="33277"><mod>mode</mod></f><f n="hcut.exe" o="marheit" g="staff" p="33277"><mod>mode</mod></f><f n="header.exe" o="marheit" g="staff" p="33277"><mod>mode</mod></f><f n="histok.exe" o="marheit" g="staff" p="33277"><mod>mode</mod></f><f n="image_convert.exe" o="marheit" g="staff" p="33277"><mod>mode</mod></f><f n="labelh.exe" o="marheit" g="staff" p="33277"><mod>mode</mod></f><f n="laserplot.exe" o="marheit" g="staff" p="33277"><mod>mode</mod></f><f n="latlinprescal.exe" o="marheit" g="staff" p="33277"><mod>mode</mod></f><f n="masktrana.exe" o="marheit" g="staff" p="33277"><mod>mode</mod></f><f n="mmtomklcf.exe" o="marheit" g="staff" p="33277"><mod>mode</mod></f><f n="mrc2tif.exe" o="marheit" g="staff" p="33277"><mod>mode</mod></f><f n="oddremove.exe" o="marheit" g="staff" p="33277"><mod>mode</mod></f><f n="padbox.exe" o="marheit" g="staff" p="33277"><mod>mode</mod></f><f n="prepmklcf.exe" o="marheit" g="staff" p="33277"><mod>mode</mod></f><f n="refineorigin.exe" o="marheit" g="staff" p="33277"><mod>mode</mod></f><f n="scalimamp3d.exe" o="marheit" g="staff" p="33277"><mod>mode</mod></f><f n="tif2mrc.exe" o="marheit" g="staff" p="33277"><mod>mode</mod></f><f n="trmask.exe" o="marheit" g="staff" p="33277"><mod>mode</mod></f><f n="twofile.exe" o="marheit" g="staff" p="33277"><mod>mode</mod></f><f n="twolattk.exe" o="marheit" g="staff" p="33277"><mod>mode</mod></f><mod>mode</mod></f><f n="scripts-custom" o="marheit" g="staff" p="16893"><f n="2dx_all_parameters.script" o="marheit" g="staff" p="33277"><mod>mode</mod></f><f n="2dx_backup.script" o="marheit" g="staff" p="33277"><mod>mode</mod></f><f n="2dx_cleanup.script" o="marheit" g="staff" p="33277"><mod>mode</mod></f><f n="2dx_copyMerge.script" o="marheit" g="staff" p="33277"><mod>mode</mod></f><f n="2dx_DetermineSwitch.script" o="marheit" g="staff" p="33277"><mod>mode</mod></f><f n="2dx_genMergeMapRegister.script" o="marheit" g="staff" p="33277"><mod>mode</mod></f><f n="2dx_import_large.script" o="marheit" g="staff" p="33277"><mod>mode</mod></f><f n="2dx_inventory.script" o="marheit" g="staff" p="33277"><mod>mode</mod></f><f n="2dx_mapdisplay.script" o="marheit" g="staff" p="33277"><mod>mode</mod></f><f n="2dx_MaximumLikelihood.script" o="marheit" g="staff" p="33277"><mod>mode</mod></f><f n="2dx_mergeCustom.script" o="marheit" g="staff" p="33277"><mod>mode</mod></f><f n="2dx_modifyImageParameter.script" o="marheit" g="staff" p="33277"><mod>mode</mod></f><f n="2dx_refreshData.script" o="marheit" g="staff" p="33277"><mod>mode</mod></f><f n="BACKUP" o="marheit" g="staff" p="16893"><f n="Custom-1.script" o="marheit" g="staff" p="33277"><mod>mode</mod></f><f n="Custom-2.script" o="marheit" g="staff" p="33277"><mod>mode</mod></f><f n="Custom-3.script" o="marheit" g="staff" p="33277"><mod>mode</mod></f><mod>mode</mod></f><f n="Custom-1.script" o="marheit" g="staff" p="33277"><mod>mode</mod></f><f n="Custom-2.script" o="marheit" g="staff" p="33277"><mod>mode</mod></f><f n="Custom-3.script" o="marheit" g="staff" p="33277"><mod>mode</mod></f><mod>mode</mod></f><f n="scripts-standard" o="marheit" g="staff" p="16893"><f n="2dx_finalmerge.script" o="marheit" g="staff" p="33277"><mod>mode</mod></f><f n="2dx_generateImageMaps.script" o="marheit" g="staff" p="33277"><mod>mode</mod></f><f n="2dx_generateMergeMap.script" o="marheit" g="staff" p="33277"><mod>mode</mod></f><f n="2dx_initialize.script" o="marheit" g="staff" p="33277"><mod>mode</mod></f><f n="2dx_merge.script" o="marheit" g="staff" p="33277"><mod>mode</mod></f><f n="2dx_mergeRefine.script" o="marheit" g="staff" p="33277"><mod>mode</mod></f><f n="2dx_refine.script" o="marheit" g="staff" p="33277"><mod>mode</mod></f><f n="2dx_reunbend.script" o="marheit" g="staff" p="33277"><mod>mode</mod></f><mod>mode</mod></f><mod>mode</mod></f><f n="bin" o="marheit" g="staff" p="16893"><f n="2dx_image" o="marheit" g="staff" p="33277"><mod>mode</mod></f><f n="2dx_logbrowser" o="marheit" g="staff" p="33277"><mod>mode</mod></f><f n="2dx_merge" o="marheit" g="staff" p="33277"><mod>mode</mod></f><mod>mode</mod></f><f n="build" o="marheit" g="staff" p="16893"><f n="conf" o="marheit" g="staff" p="16893"><f n="__" o="marheit" g="staff" p="16893"><f n="__" o="marheit" g="staff" p="16893"><f n="__" o="marheit" g="staff" p="16893"><f n="include" o="marheit" g="staff" p="16893"><f n="moc_confData.cxx" o="marheit" g="staff" p="33204"><mod>mode</mod></f><f n="moc_confDelegate.cxx" o="marheit" g="staff" p="33204"><mod>mode</mod></f><f n="moc_confEditor.cxx" o="marheit" g="staff" p="33204"><mod>mode</mod></f><f n="moc_confElement.cxx" o="marheit" g="staff" p="33204"><mod>mode</mod></f><f n="moc_confInput.cxx" o="marheit" g="staff" p="33204"><mod>mode</mod></f><f n="moc_confInterface.cxx" o="marheit" g="staff" p="33204"><mod>mode</mod></f><f n="moc_confManual.cxx" o="marheit" g="staff" p="33204"><mod>mode</mod></f><f n="moc_confModel.cxx" o="marheit" g="staff" p="33204"><mod>mode</mod></f><f n="moc_confSection.cxx" o="marheit" g="staff" p="33204"><mod>mode</mod></f><f n="moc_confSectionHeader.cxx" o="marheit" g="staff" p="33204"><mod>mode</mod></f><f n="moc_confValidator.cxx" o="marheit" g="staff" p="33204"><mod>mode</mod></f><mod>mode</mod></f><mod>mode</mod></f><mod>mode</mod></f><mod>mode</mod></f><f n="cmake_install.cmake" o="marheit" g="staff" p="33204"><mod>mode</mod></f><f n="CMakeCache.txt" o="marheit" g="staff" p="33204"><mod>mode</mod></f><f n="CMakeFiles" o="marheit" g="staff" p="16893"><f n="cmake.check_cache" o="marheit" g="staff" p="33204"><mod>mode</mod></f><f n="CMakeCCompiler.cmake" o="marheit" g="staff" p="33204"><mod>mode</mod></f><f n="CMakeCXXCompiler.cmake" o="marheit" g="staff" p="33204"><mod>mode</mod></f><f n="CMakeDetermineCompilerABI_C.bin" o="marheit" g="staff" p="33277"><mod>mode</mod></f><f n="CMakeDetermineCompilerABI_CXX.bin" o="marheit" g="staff" p="33277"><mod>mode</mod></f><f n="CMakeDirectoryInformation.cmake" o="marheit" g="staff" p="33204"><mod>mode</mod></f><f n="CMakeError.log" o="marheit" g="staff" p="33204"><mod>mode</mod></f><f n="CMakeOutput.log" o="marheit" g="staff" p="33204"><mod>mode</mod></f><f n="CMakeRuleHashes.txt" o="marheit" g="staff" p="33204"><mod>mode</mod></f><f n="CMakeSystem.cmake" o="marheit" g="staff" p="33204"><mod>mode</mod></f><f n="CMakeTmp" o="marheit" g="staff" p="16893"><f n="CMakeFiles" o="marheit" g="staff" p="16893"><f n="cmTryCompileExec.dir" o="marheit" g="staff" p="16893"><mod>mode</mod></f><mod>mode</mod></f><mod>mode</mod></f><f n="CompilerIdC" o="marheit" g="staff" p="16893"><f n="a.out" o="marheit" g="staff" p="33277"><mod>mode</mod></f><f n="CMakeCCompilerId.c" o="marheit" g="staff" p="33204"><mod>mode</mod></f><mod>mode</mod></f><f n="CompilerIdCXX" o="marheit" g="staff" p="16893"><f n="a.out" o="marheit" g="staff" p="33277"><mod>mode</mod></f><f n="CMakeCXXCompilerId.cpp" o="marheit" g="staff" p="33204"><mod>mode</mod></f><mod>mode</mod></f><f n="conf.dir" o="marheit" g="staff" p="16893"><f n="__" o="marheit" g="staff" p="16893"><f n="__" o="marheit" g="staff" p="16893"><f n="__" o="marheit" g="staff" p="16893"><f n="include" o="marheit" g="staff" p="16893"><f n="moc_confData.cxx.o" o="marheit" g="staff" p="33204"><mod>mode</mod></f><f n="moc_confDelegate.cxx.o" o="marheit" g="staff" p="33204"><mod>mode</mod></f><f n="moc_confEditor.cxx.o" o="marheit" g="staff" p="33204"><mod>mode</mod></f><f n="moc_confElement.cxx.o" o="marheit" g="staff" p="33204"><mod>mode</mod></f><f n="moc_confInput.cxx.o" o="marheit" g="staff" p="33204"><mod>mode</mod></f><f n="moc_confInterface.cxx.o" o="marheit" g="staff" p="33204"><mod>mode</mod></f><f n="moc_confManual.cxx.o" o="marheit" g="staff" p="33204"><mod>mode</mod></f><f n="moc_confModel.cxx.o" o="marheit" g="staff" p="33204"><mod>mode</mod></f><f n="moc_confSection.cxx.o" o="marheit" g="staff" p="33204"><mod>mode</mod></f><f n="moc_confSectionHeader.cxx.o" o="marheit" g="staff" p="33204"><mod>mode</mod></f><f n="moc_confValidator.cxx.o" o="marheit" g="staff" p="33204"><mod>mode</mod></f><mod>mode</mod></f><mod>mode</mod></f><mod>mode</mod></f><mod>mode</mod></f><f n="build.make" o="marheit" g="staff" p="33204"><mod>mode</mod></f><f n="cmake_clean.cmake" o="marheit" g="staff" p="33204"><mod>mode</mod></f><f n="cmake_clean_target.cmake" o="marheit" g="staff" p="33204"><mod>mode</mod></f><f n="confData.cpp.o" o="marheit" g="staff" p="33204"><mod>mode</mod></f><f n="confDelegate.cpp.o" o="marheit" g="staff" p="33204"><mod>mode</mod></f><f n="confElement.cpp.o" o="marheit" g="staff" p="33204"><mod>mode</mod></f><f n="confSection.cpp.o" o="marheit" g="staff" p="33204"><mod>mode</mod></f><f n="CXX.includecache" o="marheit" g="staff" p="33204"><mod>mode</mod></f><f n="depend.internal" o="marheit" g="staff" p="33204"><mod>mode</mod></f><f n="depend.make" o="marheit" g="staff" p="33204"><mod>mode</mod></f><f n="DependInfo.cmake" o="marheit" g="staff" p="33204"><mod>mode</mod></f><f n="flags.make" o="marheit" g="staff" p="33204"><mod>mode</mod></f><f n="link.txt" o="marheit" g="staff" p="33204"><mod>mode</mod></f><f n="progress.make" o="marheit" g="staff" p="33204"><mod>mode</mod></f><mod>mode</mod></f><f n="Makefile.cmake" o="marheit" g="staff" p="33204"><mod>mode</mod></f><f n="Makefile2" o="marheit" g="staff" p="33204"><mod>mode</mod></f><f n="progress.marks" o="marheit" g="staff" p="33204"><mod>mode</mod></f><f n="TargetDirectories.txt" o="marheit" g="staff" p="33204"><mod>mode</mod></f><mod>mode</mod></f><f n="install_manifest.txt" o="marheit" g="staff" p="33204"><mod>mode</mod></f><f n="libconf.a" o="marheit" g="staff" p="33204"><mod>mode</mod></f><f n="Makefile" o="marheit" g="staff" p="33204"><mod>mode</mod></f><f n="share" o="marheit" g="staff" p="16893"><f n="conf-1" o="marheit" g="staff" p="16893"><f n="confConfig.cmake" o="marheit" g="staff" p="33204"><mod>mode</mod></f><f n="confConfigVersion.cmake" o="marheit" g="staff" p="33204"><mod>mode</mod></f><mod>mode</mod></f><mod>mode</mod></f><mod>mode</mod></f><f n="extentions" o="marheit" g="staff" p="16893"><f n="__" o="marheit" g="staff" p="16893"><f n="__" o="marheit" g="staff" p="16893"><f n="__" o="marheit" g="staff" p="16893"><f n="include" o="marheit" g="staff" p="16893"><f n="moc_fileWatcher.cxx" o="marheit" g="staff" p="33204"><mod>mode</mod></f><f n="moc_scriptParser.cxx" o="marheit" g="staff" p="33204"><mod>mode</mod></f><mod>mode</mod></f><mod>mode</mod></f><mod>mode</mod></f><mod>mode</mod></f><f n="cmake_install.cmake" o="marheit" g="staff" p="33204"><mod>mode</mod></f><f n="CMakeCache.txt" o="marheit" g="staff" p="33204"><mod>mode</mod></f><f n="CMakeFiles" o="marheit" g="staff" p="16893"><f n="cmake.check_cache" o="marheit" g="staff" p="33204"><mod>mode</mod></f><f n="CMakeCCompiler.cmake" o="marheit" g="staff" p="33204"><mod>mode</mod></f><f n="CMakeCXXCompiler.cmake" o="marheit" g="staff" p="33204"><mod>mode</mod></f><f n="CMakeDetermineCompilerABI_C.bin" o="marheit" g="staff" p="33277"><mod>mode</mod></f><f n="CMakeDetermineCompilerABI_CXX.bin" o="marheit" g="staff" p="33277"><mod>mode</mod></f><f n="CMakeDirectoryInformation.cmake" o="marheit" g="staff" p="33204"><mod>mode</mod></f><f n="CMakeError.log" o="marheit" g="staff" p="33204"><mod>mode</mod></f><f n="CMakeOutput.log" o="marheit" g="staff" p="33204"><mod>mode</mod></f><f n="CMakeRuleHashes.txt" o="marheit" g="staff" p="33204"><mod>mode</mod></f><f n="CMakeSystem.cmake" o="marheit" g="staff" p="33204"><mod>mode</mod></f><f n="CMakeTmp" o="marheit" g="staff" p="16893"><f n="CMakeFiles" o="marheit" g="staff" p="16893"><f n="cmTryCompileExec.dir" o="marheit" g="staff" p="16893"><mod>mode</mod></f><mod>mode</mod></f><mod>mode</mod></f><f n="CompilerIdC" o="marheit" g="staff" p="16893"><f n="a.out" o="marheit" g="staff" p="33277"><mod>mode</mod></f><f n="CMakeCCompilerId.c" o="marheit" g="staff" p="33204"><mod>mode</mod></f><mod>mode</mod></f><f n="CompilerIdCXX" o="marheit" g="staff" p="16893"><f n="a.out" o="marheit" g="staff" p="33277"><mod>mode</mod></f><f n="CMakeCXXCompilerId.cpp" o="marheit" g="staff" p="33204"><mod>mode</mod></f><mod>mode</mod></f><f n="extentions.dir" o="marheit" g="staff" p="16893"><f n="__" o="marheit" g="staff" p="16893"><f n="__" o="marheit" g="staff" p="16893"><f n="__" o="marheit" g="staff" p="16893"><f n="include" o="marheit" g="staff" p="16893"><f n="moc_fileWatcher.cxx.o" o="marheit" g="staff" p="33204"><mod>mode</mod></f><f n="moc_scriptParser.cxx.o" o="marheit" g="staff" p="33204"><mod>mode</mod></f><mod>mode</mod></f><mod>mode</mod></f><mod>mode</mod></f><mod>mode</mod></f><f n="build.make" o="marheit" g="staff" p="33204"><mod>mode</mod></f><f n="cmake_clean.cmake" o="marheit" g="staff" p="33204"><mod>mode</mod></f><f n="cmake_clean_target.cmake" o="marheit" g="staff" p="33204"><mod>mode</mod></f><f n="CXX.includecache" o="marheit" g="staff" p="33204"><mod>mode</mod></f><f n="depend.internal" o="marheit" g="staff" p="33204"><mod>mode</mod></f><f n="depend.make" o="marheit" g="staff" p="33204"><mod>mode</mod></f><f n="DependInfo.cmake" o="marheit" g="staff" p="33204"><mod>mode</mod></f><f n="fileWatcher.cpp.o" o="marheit" g="staff" p="33204"><mod>mode</mod></f><f n="flags.make" o="marheit" g="staff" p="33204"><mod>mode</mod></f><f n="link.txt" o="marheit" g="staff" p="33204"><mod>mode</mod></f><f n="parse_csh.cpp.o" o="marheit" g="staff" p="33204"><mod>mode</mod></f><f n="progress.make" o="marheit" g="staff" p="33204"><mod>mode</mod></f><f n="scriptParser.cpp.o" o="marheit" g="staff" p="33204"><mod>mode</mod></f><mod>mode</mod></f><f n="Makefile.cmake" o="marheit" g="staff" p="33204"><mod>mode</mod></f><f n="Makefile2" o="marheit" g="staff" p="33204"><mod>mode</mod></f><f n="progress.marks" o="marheit" g="staff" p="33204"><mod>mode</mod></f><f n="TargetDirectories.txt" o="marheit" g="staff" p="33204"><mod>mode</mod></f><mod>mode</mod></f><f n="install_manifest.txt" o="marheit" g="staff" p="33204"><mod>mode</mod></f><f n="libextentions.a" o="marheit" g="staff" p="33204"><mod>mode</mod></f><f n="Makefile" o="marheit" g="staff" p="33204"><mod>mode</mod></f><f n="share" o="marheit" g="staff" p="16893"><f n="extentions-1" o="marheit" g="staff" p="16893"><f n="extentionsConfig.cmake" o="marheit" g="staff" p="33204"><mod>mode</mod></f><f n="extentionsConfigVersion.cmake" o="marheit" g="staff" p="33204"><mod>mode</mod></f><mod>mode</mod></f><mod>mode</mod></f><mod>mode</mod></f><f n="mrcImage" o="marheit" g="staff" p="16893"><f n="__" o="marheit" g="staff" p="16893"><f n="__" o="marheit" g="staff" p="16893"><f n="__" o="marheit" g="staff" p="16893"><f n="include" o="marheit" g="staff" p="16893"><f n="moc_largeMRC.cxx" o="marheit" g="staff" p="33204"><mod>mode</mod></f><f n="moc_mrcImage.cxx" o="marheit" g="staff" p="33204"><mod>mode</mod></f><f n="moc_mrcImageFast.cxx" o="marheit" g="staff" p="33204"><mod>mode</mod></f><mod>mode</mod></f><mod>mode</mod></f><mod>mode</mod></f><mod>mode</mod></f><f n="cmake_install.cmake" o="marheit" g="staff" p="33204"><mod>mode</mod></f><f n="CMakeCache.txt" o="marheit" g="staff" p="33204"><mod>mode</mod></f><f n="CMakeFiles" o="marheit" g="staff" p="16893"><f n="cmake.check_cache" o="marheit" g="staff" p="33204"><mod>mode</mod></f><f n="CMakeCCompiler.cmake" o="marheit" g="staff" p="33204"><mod>mode</mod></f><f n="CMakeCXXCompiler.cmake" o="marheit" g="staff" p="33204"><mod>mode</mod></f><f n="CMakeDetermineCompilerABI_C.bin" o="marheit" g="staff" p="33277"><mod>mode</mod></f><f n="CMakeDetermineCompilerABI_CXX.bin" o="marheit" g="staff" p="33277"><mod>mode</mod></f><f n="CMakeDirectoryInformation.cmake" o="marheit" g="staff" p="33204"><mod>mode</mod></f><f n="CMakeError.log" o="marheit" g="staff" p="33204"><mod>mode</mod></f><f n="CMakeOutput.log" o="marheit" g="staff" p="33204"><mod>mode</mod></f><f n="CMakeRuleHashes.txt" o="marheit" g="staff" p="33204"><mod>mode</mod></f><f n="CMakeSystem.cmake" o="marheit" g="staff" p="33204"><mod>mode</mod></f><f n="CMakeTmp" o="marheit" g="staff" p="16893"><f n="CMakeFiles" o="marheit" g="staff" p="16893"><f n="cmTryCompileExec.dir" o="marheit" g="staff" p="16893"><mod>mode</mod></f><mod>mode</mod></f><mod>mode</mod></f><f n="CompilerIdC" o="marheit" g="staff" p="16893"><f n="a.out" o="marheit" g="staff" p="33277"><mod>mode</mod></f><f n="CMakeCCompilerId.c" o="marheit" g="staff" p="33204"><mod>mode</mod></f><mod>mode</mod></f><f n="CompilerIdCXX" o="marheit" g="staff" p="16893"><f n="a.out" o="marheit" g="staff" p="33277"><mod>mode</mod></f><f n="CMakeCXXCompilerId.cpp" o="marheit" g="staff" p="33204"><mod>mode</mod></f><mod>mode</mod></f><f n="Makefile.cmake" o="marheit" g="staff" p="33204"><mod>mode</mod></f><f n="Makefile2" o="marheit" g="staff" p="33204"><mod>mode</mod></f><f n="mrcImage.dir" o="marheit" g="staff" p="16893"><f n="__" o="marheit" g="staff" p="16893"><f n="__" o="marheit" g="staff" p="16893"><f n="__" o="marheit" g="staff" p="16893"><f n="include" o="marheit" g="staff" p="16893"><f n="moc_largeMRC.cxx.o" o="marheit" g="staff" p="33204"><mod>mode</mod></f><f n="moc_mrcImage.cxx.o" o="marheit" g="staff" p="33204"><mod>mode</mod></f><f n="moc_mrcImageFast.cxx.o" o="marheit" g="staff" p="33204"><mod>mode</mod></f><mod>mode</mod></f><mod>mode</mod></f><mod>mode</mod></f><mod>mode</mod></f><f n="build.make" o="marheit" g="staff" p="33204"><mod>mode</mod></f><f n="cmake_clean.cmake" o="marheit" g="staff" p="33204"><mod>mode</mod></f><f n="cmake_clean_target.cmake" o="marheit" g="staff" p="33204"><mod>mode</mod></f><f n="CXX.includecache" o="marheit" g="staff" p="33204"><mod>mode</mod></f><f n="depend.internal" o="marheit" g="staff" p="33204"><mod>mode</mod></f><f n="depend.make" o="marheit" g="staff" p="33204"><mod>mode</mod></f><f n="DependInfo.cmake" o="marheit" g="staff" p="33204"><mod>mode</mod></f><f n="flags.make" o="marheit" g="staff" p="33204"><mod>mode</mod></f><f n="largeMRC.cpp.o" o="marheit" g="staff" p="33204"><mod>mode</mod></f><f n="link.txt" o="marheit" g="staff" p="33204"><mod>mode</mod></f><f n="mrcHeader.cpp.o" o="marheit" g="staff" p="33204"><mod>mode</mod></f><f n="mrcImage.cpp.o" o="marheit" g="staff" p="33204"><mod>mode</mod></f><f n="progress.make" o="marheit" g="staff" p="33204"><mod>mode</mod></f><f n="threadedLoad.cpp.o" o="marheit" g="staff" p="33204"><mod>mode</mod></f><mod>mode</mod></f><f n="progress.marks" o="marheit" g="staff" p="33204"><mod>mode</mod></f><f n="TargetDirectories.txt" o="marheit" g="staff" p="33204"><mod>mode</mod></f><mod>mode</mod></f><f n="install_manifest.txt" o="marheit" g="staff" p="33204"><mod>mode</mod></f><f n="libmrcImage.a" o="marheit" g="staff" p="33204"><mod>mode</mod></f><f n="Makefile" o="marheit" g="staff" p="33204"><mod>mode</mod></f><f n="share" o="marheit" g="staff" p="16893"><f n="mrcImage-1" o="marheit" g="staff" p="16893"><f n="mrcImageConfig.cmake" o="marheit" g="staff" p="33204"><mod>mode</mod></f><f n="mrcImageConfigVersion.cmake" o="marheit" g="staff" p="33204"><mod>mode</mod></f><mod>mode</mod></f><mod>mode</mod></f><mod>mode</mod></f><f n="widgets" o="marheit" g="staff" p="16893"><f n="__" o="marheit" g="staff" p="16893"><f n="__" o="marheit" g="staff" p="16893"><f n="__" o="marheit" g="staff" p="16893"><f n="include" o="marheit" g="staff" p="16893"><f n="moc_aboutWindow.cxx" o="marheit" g="staff" p="33204"><mod>mode</mod></f><f n="moc_abstractTool.cxx" o="marheit" g="staff" p="33204"><mod>mode</mod></f><f n="moc_colorTool.cxx" o="marheit" g="staff" p="33204"><mod>mode</mod></f><f n="moc_confEditor.cxx" o="marheit" g="staff" p="33204"><mod>mode</mod></f><f n="moc_confInput.cxx" o="marheit" g="staff" p="33204"><mod>mode</mod></f><f n="moc_confInterface.cxx" o="marheit" g="staff" p="33204"><mod>mode</mod></f><f n="moc_confManual.cxx" o="marheit" g="staff" p="33204"><mod>mode</mod></f><f n="moc_confModel.cxx" o="marheit" g="staff" p="33204"><mod>mode</mod></f><f n="moc_confSectionHeader.cxx" o="marheit" g="staff" p="33204"><mod>mode</mod></f><f n="moc_confValidator.cxx" o="marheit" g="staff" p="33204"><mod>mode</mod></f><f n="moc_controlBar.cxx" o="marheit" g="staff" p="33204"><mod>mode</mod></f><f n="moc_ctfTool.cxx" o="marheit" g="staff" p="33204"><mod>mode</mod></f><f n="moc_displayParametersTool.cxx" o="marheit" g="staff" p="33204"><mod>mode</mod></f><f n="moc_fullScreenImage.cxx" o="marheit" g="staff" p="33204"><mod>mode</mod></f><f n="moc_glWidget.cxx" o="marheit" g="staff" p="33204"><mod>mode</mod></f><f n="moc_graphicalButton.cxx" o="marheit" g="staff" p="33204"><mod>mode</mod></f><f n="moc_imageNavigator.cxx" o="marheit" g="staff" p="33204"><mod>mode</mod></f><f n="moc_imagePreview.cxx" o="marheit" g="staff" p="33204"><mod>mode</mod></f><f n="moc_imageViewer.cxx" o="marheit" g="staff" p="33204"><mod>mode</mod></f><f n="moc_latticeRefineTool.cxx" o="marheit" g="staff" p="33204"><mod>mode</mod></f><f n="moc_latticeTool.cxx" o="marheit" g="staff" p="33204"><mod>mode</mod></f><f n="moc_levelGroup.cxx" o="marheit" g="staff" p="33204"><mod>mode</mod></f><f n="moc_LogViewer.cxx" o="marheit" g="staff" p="33204"><mod>mode</mod></f><f n="moc_mouseAssignTool.cxx" o="marheit" g="staff" p="33204"><mod>mode</mod></f><f n="moc_mrcGraphicsItem.cxx" o="marheit" g="staff" p="33204"><mod>mode</mod></f><f n="moc_phaseView.cxx" o="marheit" g="staff" p="33204"><mod>mode</mod></f><f n="moc_resizeableStackedWidget.cxx" o="marheit" g="staff" p="33204"><mod>mode</mod></f><f n="moc_scriptModule.cxx" o="marheit" g="staff" p="33204"><mod>mode</mod></f><f n="moc_scriptProgress.cxx" o="marheit" g="staff" p="33204"><mod>mode</mod></f><f n="moc_selectionFFT.cxx" o="marheit" g="staff" p="33204"><mod>mode</mod></f><f n="moc_SpinBoxDelegate.cxx" o="marheit" g="staff" p="33204"><mod>mode</mod></f><f n="moc_spotSelectTool.cxx" o="marheit" g="staff" p="33204"><mod>mode</mod></f><f n="moc_textBrowser.cxx" o="marheit" g="staff" p="33204"><mod>mode</mod></f><f n="moc_updateWindow.cxx" o="marheit" g="staff" p="33204"><mod>mode</mod></f><f n="moc_viewContainer.cxx" o="marheit" g="staff" p="33204"><mod>mode</mod></f><f n="moc_zoomWindow.cxx" o="marheit" g="staff" p="33204"><mod>mode</mod></f><mod>mode</mod></f><mod>mode</mod></f><mod>mode</mod></f><mod>mode</mod></f><f n="cmake_install.cmake" o="marheit" g="staff" p="33204"><mod>mode</mod></f><f n="CMakeCache.txt" o="marheit" g="staff" p="33204"><mod>mode</mod></f><f n="CMakeFiles" o="marheit" g="staff" p="16893"><f n="cmake.check_cache" o="marheit" g="staff" p="33204"><mod>mode</mod></f><f n="CMakeCCompiler.cmake" o="marheit" g="staff" p="33204"><mod>mode</mod></f><f n="CMakeCXXCompiler.cmake" o="marheit" g="staff" p="33204"><mod>mode</mod></f><f n="CMakeDetermineCompilerABI_C.bin" o="marheit" g="staff" p="33277"><mod>mode</mod></f><f n="CMakeDetermineCompilerABI_CXX.bin" o="marheit" g="staff" p="33277"><mod>mode</mod></f><f n="CMakeDirectoryInformation.cmake" o="marheit" g="staff" p="33204"><mod>mode</mod></f><f n="CMakeError.log" o="marheit" g="staff" p="33204"><mod>mode</mod></f><f n="CMakeOutput.log" o="marheit" g="staff" p="33204"><mod>mode</mod></f><f n="CMakeRuleHashes.txt" o="marheit" g="staff" p="33204"><mod>mode</mod></f><f n="CMakeSystem.cmake" o="marheit" g="staff" p="33204"><mod>mode</mod></f><f n="CMakeTmp" o="marheit" g="staff" p="16893"><f n="CMakeFiles" o="marheit" g="staff" p="16893"><f n="cmTryCompileExec.dir" o="marheit" g="staff" p="16893"><mod>mode</mod></f><mod>mode</mod></f><mod>mode</mod></f><f n="CompilerIdC" o="marheit" g="staff" p="16893"><f n="a.out" o="marheit" g="staff" p="33277"><mod>mode</mod></f><f n="CMakeCCompilerId.c" o="marheit" g="staff" p="33204"><mod>mode</mod></f><mod>mode</mod></f><f n="CompilerIdCXX" o="marheit" g="staff" p="16893"><f n="a.out" o="marheit" g="staff" p="33277"><mod>mode</mod></f><f n="CMakeCXXCompilerId.cpp" o="marheit" g="staff" p="33204"><mod>mode</mod></f><mod>mode</mod></f><f n="Makefile.cmake" o="marheit" g="staff" p="33204"><mod>mode</mod></f><f n="Makefile2" o="marheit" g="staff" p="33204"><mod>mode</mod></f><f n="progress.marks" o="marheit" g="staff" p="33204"><mod>mode</mod></f><f n="TargetDirectories.txt" o="marheit" g="staff" p="33204"><mod>mode</mod></f><f n="widgets.dir" o="marheit" g="staff" p="16893"><f n="__" o="marheit" g="staff" p="16893"><f n="__" o="marheit" g="staff" p="16893"><f n="__" o="marheit" g="staff" p="16893"><f n="include" o="marheit" g="staff" p="16893"><f n="moc_aboutWindow.cxx.o" o="marheit" g="staff" p="33204"><mod>mode</mod></f><f n="moc_abstractTool.cxx.o" o="marheit" g="staff" p="33204"><mod>mode</mod></f><f n="moc_colorTool.cxx.o" o="marheit" g="staff" p="33204"><mod>mode</mod></f><f n="moc_confEditor.cxx.o" o="marheit" g="staff" p="33204"><mod>mode</mod></f><f n="moc_confInput.cxx.o" o="marheit" g="staff" p="33204"><mod>mode</mod></f><f n="moc_confInterface.cxx.o" o="marheit" g="staff" p="33204"><mod>mode</mod></f><f n="moc_confManual.cxx.o" o="marheit" g="staff" p="33204"><mod>mode</mod></f><f n="moc_confModel.cxx.o" o="marheit" g="staff" p="33204"><mod>mode</mod></f><f n="moc_confSectionHeader.cxx.o" o="marheit" g="staff" p="33204"><mod>mode</mod></f><f n="moc_confValidator.cxx.o" o="marheit" g="staff" p="33204"><mod>mode</mod></f><f n="moc_controlBar.cxx.o" o="marheit" g="staff" p="33204"><mod>mode</mod></f><f n="moc_ctfTool.cxx.o" o="marheit" g="staff" p="33204"><mod>mode</mod></f><f n="moc_displayParametersTool.cxx.o" o="marheit" g="staff" p="33204"><mod>mode</mod></f><f n="moc_fullScreenImage.cxx.o" o="marheit" g="staff" p="33204"><mod>mode</mod></f><f n="moc_glWidget.cxx.o" o="marheit" g="staff" p="33204"><mod>mode</mod></f><f n="moc_graphicalButton.cxx.o" o="marheit" g="staff" p="33204"><mod>mode</mod></f><f n="moc_imageNavigator.cxx.o" o="marheit" g="staff" p="33204"><mod>mode</mod></f><f n="moc_imagePreview.cxx.o" o="marheit" g="staff" p="33204"><mod>mode</mod></f><f n="moc_imageViewer.cxx.o" o="marheit" g="staff" p="33204"><mod>mode</mod></f><f n="moc_latticeRefineTool.cxx.o" o="marheit" g="staff" p="33204"><mod>mode</mod></f><f n="moc_latticeTool.cxx.o" o="marheit" g="staff" p="33204"><mod>mode</mod></f><f n="moc_levelGroup.cxx.o" o="marheit" g="staff" p="33204"><mod>mode</mod></f><f n="moc_LogViewer.cxx.o" o="marheit" g="staff" p="33204"><mod>mode</mod></f><f n="moc_mouseAssignTool.cxx.o" o="marheit" g="staff" p="33204"><mod>mode</mod></f><f n="moc_mrcGraphicsItem.cxx.o" o="marheit" g="staff" p="33204"><mod>mode</mod></f><f n="moc_phaseView.cxx.o" o="marheit" g="staff" p="33204"><mod>mode</mod></f><f n="moc_resizeableStackedWidget.cxx.o" o="marheit" g="staff" p="33204"><mod>mode</mod></f><f n="moc_scriptModule.cxx.o" o="marheit" g="staff" p="33204"><mod>mode</mod></f><f n="moc_scriptProgress.cxx.o" o="marheit" g="staff" p="33204"><mod>mode</mod></f><f n="moc_selectionFFT.cxx.o" o="marheit" g="staff" p="33204"><mod>mode</mod></f><f n="moc_SpinBoxDelegate.cxx.o" o="marheit" g="staff" p="33204"><mod>mode</mod></f><f n="moc_spotSelectTool.cxx.o" o="marheit" g="staff" p="33204"><mod>mode</mod></f><f n="moc_textBrowser.cxx.o" o="marheit" g="staff" p="33204"><mod>mode</mod></f><f n="moc_updateWindow.cxx.o" o="marheit" g="staff" p="33204"><mod>mode</mod></f><f n="moc_viewContainer.cxx.o" o="marheit" g="staff" p="33204"><mod>mode</mod></f><f n="moc_zoomWindow.cxx.o" o="marheit" g="staff" p="33204"><mod>mode</mod></f><mod>mode</mod></f><mod>mode</mod></f><mod>mode</mod></f><mod>mode</mod></f><f n="aboutWindow.cpp.o" o="marheit" g="staff" p="33204"><mod>mode</mod></f><f n="abstractTool.cpp.o" o="marheit" g="staff" p="33204"><mod>mode</mod></f><f n="autoImportTool.cpp.o" o="marheit" g="staff" p="33204"><mod>mode</mod></f><f n="build.make" o="marheit" g="staff" p="33204"><mod>mode</mod></f><f n="cmake_clean.cmake" o="marheit" g="staff" p="33204"><mod>mode</mod></f><f n="cmake_clean_target.cmake" o="marheit" g="staff" p="33204"><mod>mode</mod></f><f n="colorTool.cpp.o" o="marheit" g="staff" p="33204"><mod>mode</mod></f><f n="confEditor.cpp.o" o="marheit" g="staff" p="33204"><mod>mode</mod></f><f n="confInput.cpp.o" o="marheit" g="staff" p="33204"><mod>mode</mod></f><f n="confInterface.cpp.o" o="marheit" g="staff" p="33204"><mod>mode</mod></f><f n="confManual.cpp.o" o="marheit" g="staff" p="33204"><mod>mode</mod></f><f n="confModel.cpp.o" o="marheit" g="staff" p="33204"><mod>mode</mod></f><f n="confSectionHeader.cpp.o" o="marheit" g="staff" p="33204"><mod>mode</mod></f><f n="confValidator.cpp.o" o="marheit" g="staff" p="33204"><mod>mode</mod></f><f n="controlBar.cpp.o" o="marheit" g="staff" p="33204"><mod>mode</mod></f><f n="ctfTool.cpp.o" o="marheit" g="staff" p="33204"><mod>mode</mod></f><f n="CXX.includecache" o="marheit" g="staff" p="33204"><mod>mode</mod></f><f n="depend.internal" o="marheit" g="staff" p="33204"><mod>mode</mod></f><f n="depend.make" o="marheit" g="staff" p="33204"><mod>mode</mod></f><f n="DependInfo.cmake" o="marheit" g="staff" p="33204"><mod>mode</mod></f><f n="displayParametersTool.cpp.o" o="marheit" g="staff" p="33204"><mod>mode</mod></f><f n="flags.make" o="marheit" g="staff" p="33204"><mod>mode</mod></f><f n="fullScreenImage.cpp.o" o="marheit" g="staff" p="33204"><mod>mode</mod></f><f n="glWidget.cpp.o" o="marheit" g="staff" p="33204"><mod>mode</mod></f><f n="graphicalButton.cpp.o" o="marheit" g="staff" p="33204"><mod>mode</mod></f><f n="imageNavigator.cpp.o" o="marheit" g="staff" p="33204"><mod>mode</mod></f><f n="imagePreview.cpp.o" o="marheit" g="staff" p="33204"><mod>mode</mod></f><f n="imageViewer.cpp.o" o="marheit" g="staff" p="33204"><mod>mode</mod></f><f n="importManager.cpp.o" o="marheit" g="staff" p="33204"><mod>mode</mod></f><f n="latticeRefineTool.cpp.o" o="marheit" g="staff" p="33204"><mod>mode</mod></f><f n="latticeTool.cpp.o" o="marheit" g="staff" p="33204"><mod>mode</mod></f><f n="levelGroup.cpp.o" o="marheit" g="staff" p="33204"><mod>mode</mod></f><f n="link.txt" o="marheit" g="staff" p="33204"><mod>mode</mod></f><f n="LogViewer.cpp.o" o="marheit" g="staff" p="33204"><mod>mode</mod></f><f n="mouseAssignTool.cpp.o" o="marheit" g="staff" p="33204"><mod>mode</mod></f><f n="mrcGraphicsItem.cpp.o" o="marheit" g="staff" p="33204"><mod>mode</mod></f><f n="mrcHeaderDisplay.cpp.o" o="marheit" g="staff" p="33204"><mod>mode</mod></f><f n="navigatorHelpTool.cpp.o" o="marheit" g="staff" p="33204"><mod>mode</mod></f><f n="phaseView.cpp.o" o="marheit" g="staff" p="33204"><mod>mode</mod></f><f n="progress.make" o="marheit" g="staff" p="33204"><mod>mode</mod></f><f n="resizeableStackedWidget.cpp.o" o="marheit" g="staff" p="33204"><mod>mode</mod></f><f n="scriptModule.cpp.o" o="marheit" g="staff" p="33204"><mod>mode</mod></f><f n="scriptProgress.cpp.o" o="marheit" g="staff" p="33204"><mod>mode</mod></f><f n="selectionFFT.cpp.o" o="marheit" g="staff" p="33204"><mod>mode</mod></f><f n="SpinBoxDelegate.cpp.o" o="marheit" g="staff" p="33204"><mod>mode</mod></f><f n="spotSelectTool.cpp.o" o="marheit" g="staff" p="33204"><mod>mode</mod></f><f n="textBrowser.cpp.o" o="marheit" g="staff" p="33204"><mod>mode</mod></f><f n="updateWindow.cpp.o" o="marheit" g="staff" p="33204"><mod>mode</mod></f><f n="viewContainer.cpp.o" o="marheit" g="staff" p="33204"><mod>mode</mod></f><f n="zoomWindow.cpp.o" o="marheit" g="staff" p="33204"><mod>mode</mod></f><mod>mode</mod></f><mod>mode</mod></f><f n="install_manifest.txt" o="marheit" g="staff" p="33204"><mod>mode</mod></f><f n="libwidgets.a" o="marheit" g="staff" p="33204"><mod>mode</mod></f><f n="Makefile" o="marheit" g="staff" p="33204"><mod>mode</mod></f><f n="share" o="marheit" g="staff" p="16893"><f n="widgets-1" o="marheit" g="staff" p="16893"><f n="widgetsConfig.cmake" o="marheit" g="staff" p="33204"><mod>mode</mod></f><f n="widgetsConfigVersion.cmake" o="marheit" g="staff" p="33204"><mod>mode</mod></f><mod>mode</mod></f><mod>mode</mod></f><mod>mode</mod></f><mod>mode</mod></f><f n="cmake" o="marheit" g="staff" p="16893"><f n="FindFFTW.cmake" o="marheit" g="staff" p="33204"><mod>mode</mod></f><mod>mode</mod></f><f n="config" o="marheit" g="staff" p="16893"><f n="2dx.cfg" o="marheit" g="staff" p="33277"><mod>mode</mod></f><f n="2dx.cshrc" o="marheit" g="staff" p="33277"><mod>mode</mod></f><f n="2dx_image" o="marheit" g="staff" p="16893"><f n="2dx_status.html" o="marheit" g="staff" p="33277"><mod>mode</mod></f><f n="about.htm" o="marheit" g="staff" p="33277"><mod>mode</mod></f><f n="navigator_help.htm" o="marheit" g="staff" p="33277"><mod>mode</mod></f><mod>mode</mod></f><f n="2dx_image-algo-1.jpg" o="marheit" g="staff" p="33277"><mod>mode</mod></f><f n="2dx_image-algo-2.jpg" o="marheit" g="staff" p="33277"><mod>mode</mod></f><f n="2dx_image-user.cfg" o="marheit" g="staff" p="33277"><mod>mode</mod></f><f n="2dx_master.cfg" o="marheit" g="staff" p="33277"><mod>mode</mod></f><f n="2dx_merge" o="marheit" g="staff" p="16893"><f n="importPatterns.inf" o="marheit" g="staff" p="33277"><mod>mode</mod></f><f n="projectMenu.inf" o="marheit" g="staff" p="33277"><mod>mode</mod></f><mod>mode</mod></f><f n="2dx_ML.jpg" o="marheit" g="staff" p="33277"><mod>mode</mod></f><f n="resource" o="marheit" g="staff" p="16893"><f n="2dx_fftrans.png" o="marheit" g="staff" p="33277"><mod>mode</mod></f><f n="2dx_unbend1.png" o="marheit" g="staff" p="33277"><mod>mode</mod></f><f n="2dx_unbend2.png" o="marheit" g="staff" p="33277"><mod>mode</mod></f><f n="Bug-AU.png" o="marheit" g="staff" p="33277"><mod>mode</mod></f><f n="Bug-IU.png" o="marheit" g="staff" p="33277"><mod>mode</mod></f><f n="ControlButton.psd" o="marheit" g="staff" p="33277"><mod>mode</mod></f><f n="ctf-ID.png" o="marheit" g="staff" p="33277"><mod>mode</mod></f><f n="ctf-IU.png" o="marheit" g="staff" p="33277"><mod>mode</mod></f><f n="customScriptIcon-IU.png" o="marheit" g="staff" p="33277"><mod>mode</mod></f><f n="defocus-ID.png" o="marheit" g="staff" p="33277"><mod>mode</mod></f><f n="defocus-IU.png" o="marheit" g="staff" p="33277"><mod>mode</mod></f><f n="dryRun-AD.png" o="marheit" g="staff" p="33277"><mod>mode</mod></f><f n="dryRun-AU.png" o="marheit" g="staff" p="33277"><mod>mode</mod></f><f n="dryRun-ID.png" o="marheit" g="staff" p="33277"><mod>mode</mod></f><f n="dryRun-IU.png" o="marheit" g="staff" p="33277"><mod>mode</mod></f><f n="expand-AD.png" o="marheit" g="staff" p="33277"><mod>mode</mod></f><f n="expand-AU.png" o="marheit" g="staff" p="33277"><mod>mode</mod></f><f n="expand-ID.png" o="marheit" g="staff" p="33277"><mod>mode</mod></f><f n="expand-IU.png" o="marheit" g="staff" p="33277"><mod>mode</mod></f><f n="fft-ID.png" o="marheit" g="staff" p="33277"><mod>mode</mod></f><f n="fft-IU.png" o="marheit" g="staff" p="33277"><mod>mode</mod></f><f n="gbAqua-ID.png" o="marheit" g="staff" p="33277"><mod>mode</mod></f><f n="gbAqua-IU.png" o="marheit" g="staff" p="33277"><mod>mode</mod></f><f n="gbBlue-ID.png" o="marheit" g="staff" p="33277"><mod>mode</mod></f><f n="gbBlue-IN.psd" o="marheit" g="staff" p="33277"><mod>mode</mod></f><f n="gbBlue-IU.png" o="marheit" g="staff" p="33277"><mod>mode</mod></f><f n="gbGreen-ID.png" o="marheit" g="staff" p="33277"><mod>mode</mod></f><f n="gbGreen-IN.psd" o="marheit" g="staff" p="33277"><mod>mode</mod></f><f n="gbGreen-IU.png" o="marheit" g="staff" p="33277"><mod>mode</mod></f><f n="gbOrange-ID.png" o="marheit" g="staff" p="33277"><mod>mode</mod></f><f n="gbOrange-IU.png" o="marheit" g="staff" p="33277"><mod>mode</mod></f><f n="gbPurple-ID.png" o="marheit" g="staff" p="33277"><mod>mode</mod></f><f n="gbPurple-IU.png" o="marheit" g="staff" p="33277"><mod>mode</mod></f><f n="gbRed-ID.png" o="marheit" g="staff" p="33277"><mod>mode</mod></f><f n="gbRed-IU.png" o="marheit" g="staff" p="33277"><mod>mode</mod></f><f n="GlassButton.psd" o="marheit" g="staff" p="33277"><mod>mode</mod></f><f n="help-AD.png" o="marheit" g="staff" p="33277"><mod>mode</mod></f><f n="help-AU.png" o="marheit" g="staff" p="33277"><mod>mode</mod></f><f n="help-ID.png" o="marheit" g="staff" p="33277"><mod>mode</mod></f><f n="help-IU.png" o="marheit" g="staff" p="33277"><mod>mode</mod></f><f n="icon-2dx_image.psd" o="marheit" g="staff" p="33277"><mod>mode</mod></f><f n="icon-2dx_merge.psd" o="marheit" g="staff" p="33277"><mod>mode</mod></f><f n="icon.psd" o="marheit" g="staff" p="33277"><mod>mode</mod></f><f n="icon_OSX.icns" o="marheit" g="staff" p="33277"><mod>mode</mod></f><f n="info-AD.png" o="marheit" g="staff" p="33277"><mod>mode</mod></f><f n="info-AU.png" o="marheit" g="staff" p="33277"><mod>mode</mod></f><f n="info-ID.png" o="marheit" g="staff" p="33277"><mod>mode</mod></f><f n="info-IU.png" o="marheit" g="staff" p="33277"><mod>mode</mod></f><f n="lattice-ID.png" o="marheit" g="staff" p="33277"><mod>mode</mod></f><f n="lattice-IU.png" o="marheit" g="staff" p="33277"><mod>mode</mod></f><f n="lock-ID.png" o="marheit" g="staff" p="33277"><mod>mode</mod></f><f n="lock-IU.png" o="marheit" g="staff" p="33277"><mod>mode</mod></f><f n="Lock.psd" o="marheit" g="staff" p="33277"><mod>mode</mod></f><f n="manual-AD.png" o="marheit" g="staff" p="33277"><mod>mode</mod></f><f n="manual-AU.png" o="marheit" g="staff" p="33277"><mod>mode</mod></f><f n="manual-ID.png" o="marheit" g="staff" p="33277"><mod>mode</mod></f><f n="manual-IU.png" o="marheit" g="staff" p="33277"><mod>mode</mod></f><f n="mask-ID.png" o="marheit" g="staff" p="33277"><mod>mode</mod></f><f n="mask-IU.png" o="marheit" g="staff" p="33277"><mod>mode</mod></f><f n="merge-ID.png" o="marheit" g="staff" p="33277"><mod>mode</mod></f><f n="merge-IU.png" o="marheit" g="staff" p="33277"><mod>mode</mod></f><f n="merge.png" o="marheit" g="staff" p="33277"><mod>mode</mod></f><f n="MetalButton.psd" o="marheit" g="staff" p="33277"><mod>mode</mod></f><f n="nullPreview.png" o="marheit" g="staff" p="33277"><mod>mode</mod></f><f n="phori-ID.png" o="marheit" g="staff" p="33277"><mod>mode</mod></f><f n="phori-IU.png" o="marheit" g="staff" p="33277"><mod>mode</mod></f><f n="play-AD.png" o="marheit" g="staff" p="33277"><mod>mode</mod></f><f n="play-AU.png" o="marheit" g="staff" p="33277"><mod>mode</mod></f><f n="play-ID.png" o="marheit" g="staff" p="33277"><mod>mode</mod></f><f n="play-IU.png" o="marheit" g="staff" p="33277"><mod>mode</mod></f><f n="PostScript.psd" o="marheit" g="staff" p="33277"><mod>mode</mod></f><f n="previewControl-AD.png" o="marheit" g="staff" p="33277"><mod>mode</mod></f><f n="previewControl-AU.png" o="marheit" g="staff" p="33277"><mod>mode</mod></f><f n="previewControl-ID.png" o="marheit" g="staff" p="33277"><mod>mode</mod></f><f n="previewControl-IU.png" o="marheit" g="staff" p="33277"><mod>mode</mod></f><f n="psFile.png" o="marheit" g="staff" p="33277"><mod>mode</mod></f><f n="refresh-AD.png" o="marheit" g="staff" p="33277"><mod>mode</mod></f><f n="refresh-AU.png" o="marheit" g="staff" p="33277"><mod>mode</mod></f><f n="refresh-ID.png" o="marheit" g="staff" p="33277"><mod>mode</mod></f><f n="refresh-IU.png" o="marheit" g="staff" p="33277"><mod>mode</mod></f><f n="refresh-U.png" o="marheit" g="staff" p="33277"><mod>mode</mod></f><f n="reprocess-ID.png" o="marheit" g="staff" p="33277"><mod>mode</mod></f><f n="reprocess-IU.png" o="marheit" g="staff" p="33277"><mod>mode</mod></f><f n="save-AD.png" o="marheit" g="staff" p="33277"><mod>mode</mod></f><f n="save-AU.png" o="marheit" g="staff" p="33277"><mod>mode</mod></f><f n="save-ID.png" o="marheit" g="staff" p="33277"><mod>mode</mod></f><f n="save-IU.png" o="marheit" g="staff" p="33277"><mod>mode</mod></f><f n="saveButton-ID.psd" o="marheit" g="staff" p="33277"><mod>mode</mod></f><f n="saveDark-AD.png" o="marheit" g="staff" p="33277"><mod>mode</mod></f><f n="saveDark-AU.png" o="marheit" g="staff" p="33277"><mod>mode</mod></f><f n="saveDark-ID.png" o="marheit" g="staff" p="33277"><mod>mode</mod></f><f n="saveDark-IU.png" o="marheit" g="staff" p="33277"><mod>mode</mod></f><f n="scriptIcon-IU.png" o="marheit" g="staff" p="33277"><mod>mode</mod></f><f n="scriptIcon.psd" o="marheit" g="staff" p="33277"><mod>mode</mod></f><f n="spots-ID.png" o="marheit" g="staff" p="33277"><mod>mode</mod></f><f n="spots-IU.png" o="marheit" g="staff" p="33277"><mod>mode</mod></f><f n="subScript-IU.png" o="marheit" g="staff" p="33277"><mod>mode</mod></f><f n="textFile.png" o="marheit" g="staff" p="33277"><mod>mode</mod></f><f n="unbend-ID.png" o="marheit" g="staff" p="33277"><mod>mode</mod></f><f n="unbend-IU.png" o="marheit" g="staff" p="33277"><mod>mode</mod></f><mod>mode</mod></f><f n="status-window" o="marheit" g="staff" p="33277"><mod>mode</mod></f><f n="VARIABLE.txt" o="marheit" g="staff" p="33277"><mod>mode</mod></f><mod>mode</mod></f><f n="include" o="marheit" g="staff" p="16893"><f n="aboutWindow.h" o="marheit" g="staff" p="33204"><mod>mode</mod></f><f n="abstractTool.h" o="marheit" g="staff" p="33204"><mod>mode</mod></f><f n="autoImportTool.h" o="marheit" g="staff" p="33204"><mod>mode</mod></f><f n="colorTool.h" o="marheit" g="staff" p="33204"><mod>mode</mod></f><f n="confData.h" o="marheit" g="staff" p="33204"><mod>mode</mod></f><f n="confDelegate.h" o="marheit" g="staff" p="33204"><mod>mode</mod></f><f n="confEditor.h" o="marheit" g="staff" p="33204"><mod>mode</mod></f><f n="confElement.h" o="marheit" g="staff" p="33204"><mod>mode</mod></f><f n="confInput.h" o="marheit" g="staff" p="33204"><mod>mode</mod></f><f n="confInterface.h" o="marheit" g="staff" p="33204"><mod>mode</mod></f><f n="confManual.h" o="marheit" g="staff" p="33204"><mod>mode</mod></f><f n="confModel.h" o="marheit" g="staff" p="33204"><mod>mode</mod></f><f n="confSection.h" o="marheit" g="staff" p="33204"><mod>mode</mod></f><f n="confSectionHeader.h" o="marheit" g="staff" p="33204"><mod>mode</mod></f><f n="confValidator.h" o="marheit" g="staff" p="33204"><mod>mode</mod></f><f n="controlBar.h" o="marheit" g="staff" p="33204"><mod>mode</mod></f><f n="ctfTool.h" o="marheit" g="staff" p="33204"><mod>mode</mod></f><f n="displayParametersTool.h" o="marheit" g="staff" p="33204"><mod>mode</mod></f><f n="fileWatcher.h" o="marheit" g="staff" p="33204"><mod>mode</mod></f><f n="fullScreenImage.h" o="marheit" g="staff" p="33204"><mod>mode</mod></f><f n="glWidget.h" o="marheit" g="staff" p="33204"><mod>mode</mod></f><f n="graphicalButton.h" o="marheit" g="staff" p="33204"><mod>mode</mod></f><f n="imageNavigator.h" o="marheit" g="staff" p="33204"><mod>mode</mod></f><f n="imagePreview.h" o="marheit" g="staff" p="33204"><mod>mode</mod></f><f n="imageViewer.h" o="marheit" g="staff" p="33204"><mod>mode</mod></f><f n="importManager.h" o="marheit" g="staff" p="33204"><mod>mode</mod></f><f n="largeMRC.h" o="marheit" g="staff" p="33204"><mod>mode</mod></f><f n="latticeRefineTool.h" o="marheit" g="staff" p="33204"><mod>mode</mod></f><f n="latticeTool.h" o="marheit" g="staff" p="33204"><mod>mode</mod></f><f n="levelGroup.h" o="marheit" g="staff" p="33204"><mod>mode</mod></f><f n="LogViewer.h" o="marheit" g="staff" p="33204"><mod>mode</mod></f><f n="mouseAssignTool.h" o="marheit" g="staff" p="33204"><mod>mode</mod></f><f n="mrcGraphicsItem.h" o="marheit" g="staff" p="33204"><mod>mode</mod></f><f n="mrcHeader.h" o="marheit" g="staff" p="33204"><mod>mode</mod></f><f n="mrcHeaderDisplay.h" o="marheit" g="staff" p="33204"><mod>mode</mod></f><f n="mrcImage.h" o="marheit" g="staff" p="33204"><mod>mode</mod></f><f n="mrcImageFast.h" o="marheit" g="staff" p="33204"><mod>mode</mod></f><f n="navigatorHelpTool.h" o="marheit" g="staff" p="33204"><mod>mode</mod></f><f n="parse_csh.h" o="marheit" g="staff" p="33204"><mod>mode</mod></f><f n="phaseView.h" o="marheit" g="staff" p="33204"><mod>mode</mod></f><f n="pointHash.h" o="marheit" g="staff" p="33204"><mod>mode</mod></f><f n="resizeableStackedWidget.h" o="marheit" g="staff" p="33204"><mod>mode</mod></f><f n="scriptModule.h" o="marheit" g="staff" p="33204"><mod>mode</mod></f><f n="scriptParser.h" o="marheit" g="staff" p="33204"><mod>mode</mod></f><f n="scriptProgress.h" o="marheit" g="staff" p="33204"><mod>mode</mod></f><f n="selectionFFT.h" o="marheit" g="staff" p="33204"><mod>mode</mod></f><f n="SpinBoxDelegate.h" o="marheit" g="staff" p="33204"><mod>mode</mod></f><f n="spotSelectTool.h" o="marheit" g="staff" p="33204"><mod>mode</mod></f><f n="textBrowser.h" o="marheit" g="staff" p="33204"><mod>mode</mod></f><f n="threadedLoad.h" o="marheit" g="staff" p="33204"><mod>mode</mod></f><f n="updateWindow.h" o="marheit" g="staff" p="33204"><mod>mode</mod></f><f n="viewContainer.h" o="marheit" g="staff" p="33204"><mod>mode</mod></f><f n="zoomWindow.h" o="marheit" g="staff" p="33204"><mod>mode</mod></f><mod>mode</mod></f><f n="INSTALL.SOURCE" o="marheit" g="staff" p="33204"><mod>mode</mod></f><f n="lib" o="marheit" g="staff" p="16893"><f n="libconf.a" o="marheit" g="staff" p="33204"><mod>mode</mod></f><f n="libextentions.a" o="marheit" g="staff" p="33204"><mod>mode</mod></f><f n="libmrcImage.a" o="marheit" g="staff" p="33204"><mod>mode</mod></f><f n="libwidgets.a" o="marheit" g="staff" p="33204"><mod>mode</mod></f><mod>mode</mod></f><f n="LICENSE" o="marheit" g="staff" p="33204"><mod>mode</mod></f><f n="plugins" o="marheit" g="staff" p="16893"><f n="tools" o="marheit" g="staff" p="16893"><f n="test.js" o="marheit" g="staff" p="33277"><mod>mode</mod></f><mod>mode</mod></f><f n="translators" o="marheit" g="staff" p="16893"><f n="com.tr" o="marheit" g="staff" p="33277"><mod>mode</mod></f><f n="map.tr" o="marheit" g="staff" p="33277"><mod>mode</mod></f><f n="mtz.tr" o="marheit" g="staff" p="33277"><mod>mode</mod></f><f n="pgm.tr" o="marheit" g="staff" p="33277"><mod>mode</mod></f><mod>mode</mod></f><mod>mode</mod></f><f n="proc" o="marheit" g="staff" p="16893"><f n="2dx_checklattice_sub.com" o="marheit" g="staff" p="33277"><mod>mode</mod></f><f n="2dx_cleanup_sub.com" o="marheit" g="staff" p="33277"><mod>mode</mod></f><f n="2dx_functions.com" o="marheit" g="staff" p="33277"><mod>mode</mod></f><f n="2dx_generateMap_sub-2.com" o="marheit" g="staff" p="33277"><mod>mode</mod></f><f n="2dx_generateMap_sub.com" o="marheit" g="staff" p="33277"><mod>mode</mod></f><f n="2dx_makedirs" o="marheit" g="staff" p="33277"><mod>mode</mod></f><f n="2dx_merge_latline_sub.com" o="marheit" g="staff" p="33277"><mod>mode</mod></f><f n="2dx_merge_makedirs" o="marheit" g="staff" p="33277"><mod>mode</mod></f><f n="2dx_merge_merge_sub.com" o="marheit" g="staff" p="33277"><mod>mode</mod></f><f n="2dx_merge_redoMap_sub.com" o="marheit" g="staff" p="33277"><mod>mode</mod></f><f n="2dx_ML_sub.com" o="marheit" g="staff" p="33277"><mod>mode</mod></f><f n="2dx_refine_refine_sub.com" o="marheit" g="staff" p="33277"><mod>mode</mod></f><f n="2dx_refine_unbend1_sub.com" o="marheit" g="staff" p="33277"><mod>mode</mod></f><f n="2dx_refine_unbend2_sub.com" o="marheit" g="staff" p="33277"><mod>mode</mod></f><f n="2dx_reproject_sub.com" o="marheit" g="staff" p="33277"><mod>mode</mod></f><f n="2dx_split.com" o="marheit" g="staff" p="33277"><mod>mode</mod></f><f n="2dx_sym2spcgrp_sub.com" o="marheit" g="staff" p="33277"><mod>mode</mod></f><f n="2dx_unbend1_sub.com" o="marheit" g="staff" p="33277"><mod>mode</mod></f><f n="2dx_unbend2_sub.com" o="marheit" g="staff" p="33277"><mod>mode</mod></f><f n="2dx_unbendSyn_sub.com" o="marheit" g="staff" p="33277"><mod>mode</mod></f><f n="dummy.aph" o="marheit" g="staff" p="33277"><mod>mode</mod></f><f n="initialize" o="marheit" g="staff" p="33277"><mod>mode</mod></f><f n="lin" o="marheit" g="staff" p="33277"><mod>mode</mod></f><f n="linblock" o="marheit" g="staff" p="33277"><mod>mode</mod></f><f n="lindoubl2" o="marheit" g="staff" p="33277"><mod>mode</mod></f><f n="lindouble" o="marheit" g="staff" p="33277"><mod>mode</mod></f><f n="linhash" o="marheit" g="staff" p="33277"><mod>mode</mod></f><f n="protest" o="marheit" g="staff" p="33277"><mod>mode</mod></f><mod>mode</mod></f><f n="share" o="marheit" g="staff" p="16893"><f n="conf-1" o="marheit" g="staff" p="16893"><f n="confConfig.cmake" o="marheit" g="staff" p="33204"><mod>mode</mod></f><f n="confConfigVersion.cmake" o="marheit" g="staff" p="33204"><mod>mode</mod></f><mod>mode</mod></f><f n="extentions-1" o="marheit" g="staff" p="16893"><f n="extentionsConfig.cmake" o="marheit" g="staff" p="33204"><mod>mode</mod></f><f n="extentionsConfigVersion.cmake" o="marheit" g="staff" p="33204"><mod>mode</mod></f><mod>mode</mod></f><f n="mrcImage-1" o="marheit" g="staff" p="16893"><f n="mrcImageConfig.cmake" o="marheit" g="staff" p="33204"><mod>mode</mod></f><f n="mrcImageConfigVersion.cmake" o="marheit" g="staff" p="33204"><mod>mode</mod></f><mod>mode</mod></f><f n="widgets-1" o="marheit" g="staff" p="16893"><f n="widgetsConfig.cmake" o="marheit" g="staff" p="33204"><mod>mode</mod></f><f n="widgetsConfigVersion.cmake" o="marheit" g="staff" p="33204"><mod>mode</mod></f><mod>mode</mod></f><mod>mode</mod></f></f></pkg-contents>